MANIFEST.in
README.md
pyproject.toml
requirements_linux.txt
requirements_windows.txt
setup.py
armspeech.egg-info/PKG-INFO
armspeech.egg-info/SOURCES.txt
armspeech.egg-info/dependency_links.txt
armspeech.egg-info/entry_points.txt
armspeech.egg-info/requires.txt
armspeech.egg-info/top_level.txt
src/__init__.py
src/armspeech.py
src/armspeech_stt_cli.py
src/model/model.tflite