Metadata-Version: 2.1
Name: armspeech
Version: 0.1.3
Summary: ArmSpeech is an offline Armenian speech recognition library (speech-to-text) and CLI tool based on Coqui STT (🐸STT) and trained on the ArmSpeech dataset.
Home-page: https://github.com/Varuzhan97/armspeech
Author: Varuzhan Baghdasaryan
Author-email: varuzh2014@gmail.com
License: MIT
Project-URL: Funding, https://donate.pypi.org
Project-URL: Bug Tracker, https://github.com/Varuzhan97/armspeech/issues
Keywords: speech recognition,speech-to-text,Armenian language
Platform: UNKNOWN
Classifier: Development Status :: 3 - Alpha
Classifier: Environment :: Console
Classifier: Intended Audience :: Customer Service
Classifier: Intended Audience :: Developers
Classifier: Intended Audience :: Science/Research
Classifier: License :: OSI Approved :: MIT License
Classifier: Operating System :: OS Independent
Classifier: Programming Language :: Python
Classifier: Programming Language :: Python :: 3 :: Only
Classifier: Topic :: Home Automation
Classifier: Topic :: Multimedia :: Sound/Audio
Classifier: Topic :: Multimedia :: Sound/Audio :: Analysis
Classifier: Topic :: Multimedia :: Sound/Audio :: Speech
Classifier: Topic :: Scientific/Engineering
Classifier: Topic :: Scientific/Engineering :: Artificial Intelligence
Classifier: Topic :: Scientific/Engineering :: Human Machine Interfaces
Classifier: Topic :: Scientific/Engineering :: Information Analysis
Requires-Python: >=3.6,<3.11
